flake8_formatter_abspath/__init__.py
flake8_formatter_abspath/plugin.py
flake8_formatter_abspath-1.0.1.dist-info/DESCRIPTION.rst
flake8_formatter_abspath-1.0.1.dist-info/LICENSE.txt
flake8_formatter_abspath-1.0.1.dist-info/METADATA
flake8_formatter_abspath-1.0.1.dist-info/RECORD
flake8_formatter_abspath-1.0.1.dist-info/WHEEL
flake8_formatter_abspath-1.0.1.dist-info/entry_points.txt
flake8_formatter_abspath-1.0.1.dist-info/metadata.json
flake8_formatter_abspath-1.0.1.dist-info/top_level.txt
