Metadata-Version: 2.0
Name: flake8-formatter-abspath
Version: 1.0.1
Summary: A flake8 formatter plugin that shows the absolute path of files with warnings
Home-page: https://github.com/jarshwah/flake8_formatter_abspath
Author: Josh Smeaton
Author-email: josh.smeaton@gmail.com
License: MIT license
Keywords: flake8_formatter_abspath flake8 formatter
Platform: UNKNOWN
Classifier: Development Status :: 5 - Production/Stable
Classifier: Intended Audience :: Developers
Classifier: License :: OSI Approved :: MIT License
Classifier: Natural Language :: English
Classifier: Programming Language :: Python :: 2
Classifier: Programming Language :: Python :: 2.7
Classifier: Programming Language :: Python :: 3
Classifier: Programming Language :: Python :: 3.4
Classifier: Programming Language :: Python :: 3.5
Classifier: Programming Language :: Python :: 3.6
Requires-Dist: flake8 (>=3.0.0)
